LICENSE
README.md
setup.py
dl_fib_py/__init__.py
dl_fib_py/version.py
dl_fib_py.egg-info/PKG-INFO
dl_fib_py.egg-info/SOURCES.txt
dl_fib_py.egg-info/dependency_links.txt
dl_fib_py.egg-info/entry_points.txt
dl_fib_py.egg-info/requires.txt
dl_fib_py.egg-info/top_level.txt
dl_fib_py/cmd/__init__.py
dl_fib_py/cmd/fib_numb.py
dl_fib_py/fib_calcs/__init__.py
dl_fib_py/fib_calcs/fib_number.py
dl_fib_py/fib_calcs/fib_numbers.py
tests/dl_fib_py/__init__.py
tests/dl_fib_py/fib_calcs/__init__.py
tests/dl_fib_py/fib_calcs/test_fib_number.py
tests/dl_fib_py/fib_calcs/test_fib_numbers.py