Metadata-Version: 2.1
Name: dl-fib-py
Version: 0.0.6
Summary: Calculates a Fibonacci number
Home-page: https://github.com/dima-lurie/dl-fib-py.git
Author: Dima Lurie
Author-email: dimalurie@gmail.com
License: UNKNOWN
Platform: UNKNOWN
Classifier: Development Status :: 4 - Beta
Classifier: Programming Language :: Python :: 3
Classifier: Operating System :: OS Independent
Requires-Python: >=3.11
Provides-Extra: dev
License-File: LICENSE
